LICENSE
README.md
setup.cfg
setup.py
book_system/__init__.py
book_system/sdk.py
book_system/types/__init__.py
book_system/types/booking.py
book_system/types/events.py
book_system/types/rooms.py
book_system/types/seats.py
book_system_SKD.egg-info/PKG-INFO
book_system_SKD.egg-info/SOURCES.txt
book_system_SKD.egg-info/dependency_links.txt
book_system_SKD.egg-info/top_level.txt