Metadata-Version: 2.1
Name: book-system-SKD
Version: 0.0.1
Summary: SDK for interaction with the book-system API
Author: Artem Sydorenko
Author-email: kradworkmail@gmail.com
Classifier: Programming Language :: Python :: 3.11
Requires-Python: >=3.11
License-File: LICENSE
